{"type":"page","data":{"navigation_bar_section":{"type":"fruits-navigation-bar","data":{"brand_section":{"type":"fruits-brand-image","data":{"url":"/home","image_url":"/assets/img/logo_large.svg","image_alt":"--layout.navbar.image_alt"}},"about_us_text":"--layout.navbar.about_us_text","products_text":"--layout.navbar.products_text","language":"EN","current_url":""}},"content_sections":[{"type":"fruits-description-section","data":{"text_content_section":{"type":"fruits-articles-small-text-content","data":{"title":"--welcome.description1.title","content":"--welcome.description1.content","left_orientation":"false","button_content":"--welcome.description1.button_content","url":"/","added_classes":{".content":["mb-0"]}}},"image_url":"/assets/img/fruit_1.jpg","image_alt":"...","left_orientation":false}},{"type":"fruits-articles-small-text-content-with-two-images","data":{"title":"--welcome.article_with_two_images1.title","content":"--welcome.article_with_two_images1.content","top_image_url":"/assets/img/brand_element_01.svg","top_image_alt":"...","bottom_image_url":"/assets/img/dot.svg","bottom_image_alt":"...","added_classes":{".content":["mb-0"]}}},{"type":"fruits-articles-small-text-content-with-big-button","data":{"title":"--welcome.artical_with_big_button.title","content":"--welcome.artical_with_big_button.content","button_content":"--welcome.artical_with_big_button.button_content","url":"/","left_image_url":"/assets/img/gajjak_1.svg","left_image_alt":"...","right_image_url":"/assets/img/gajjak_2.svg","right_image_alt":"...","added_classes":{".content":["mb-0"]}}},{"type":"fruits-description-section","data":{"text_content_section":{"type":"fruits-articles-small-text-content","data":{"title":"--welcome.description2.title","content":"--welcome.description2.content","button_content":"--welcome.description2.button_content","url":"/","added_classes":{".content":["mb-0"]}}},"image_url":"/assets/img/fruit_2.jpg","image_alt":"..."}},{"type":"fruits-articles-small-text-content-with-two-images","data":{"title":"--welcome.article_with_two_images2.title","content":"--welcome.article_with_two_images2.content","top_image_url":"/assets/img/brand_element_02.svg","top_image_alt":"...","bottom_image_url":"/assets/img/dot.svg","bottom_image_alt":"...","added_classes":{".content":["mb-0"]}}},{"type":"fruits-description-section","data":{"text_content_section":{"type":"fruits-articles-small-text-content","data":{"title":"--welcome.description3.title","content":"--welcome.description3.content","button_content":"--welcome.description3.button_content","url":"/","added_classes":{".content":["mb-0"]}}},"image_url":"/assets/img/fruit_3.jpg","image_alt":"...","left_orientation":false}},{"type":"fruits-articles-small-text-content-with-two-images","data":{"title":"--welcome.article_with_two_images3.title","content":"--welcome.article_with_two_images3.content","top_image_url":"/assets/img/brand_element_01.svg","top_image_alt":"...","bottom_image_url":"/assets/img/dot.svg","bottom_image_alt":"...","added_classes":{".content":["mb-0"]}}},{"type":"fruits-articles-small-text-content-with-big-button","data":{"title":"--welcome.artical_with_big_button.title","content":"--welcome.artical_with_big_button.content","button_content":"--welcome.artical_with_big_button.button_content","url":"/","left_image_url":"/assets/img/gajjak_1.svg","left_image_alt":"...","right_image_url":"/assets/img/gajjak_2.svg","right_image_alt":"...","added_classes":{".content":["mb-0"]}}}],"footer_section":{"type":"fruits-footer","data":{"icon_links_section":{"type":"wertically-icon-links","data":{"icon_sections":[{"type":"fruits-button-icon-link","data":{"url":"","icon_class":"fab fa-facebook-f"}},{"type":"fruits-button-icon-link","data":{"url":"","icon_class":"fab fa-twitter"}},{"type":"fruits-button-icon-link","data":{"url":"","icon_class":"fas fa-envelope"}}]}},"copyright":{"address":"--layout.footer.address", "phone":"--layout.footer.phone", "email":"--layout.footer.email"},"image_url":"/assets/img/logo_small.svg","image_alt":"..."}}}}